xmcda/XMCDA.py
xmcda/__init__.py
xmcda/alternatives.py
xmcda/alternatives_assignments.py
xmcda/alternatives_matrix.py
xmcda/alternatives_sets.py
xmcda/alternatives_sets_values.py
xmcda/alternatives_values.py
xmcda/categories.py
xmcda/categories_matrix.py
xmcda/categories_profiles.py
xmcda/categories_sets.py
xmcda/categories_sets_values.py
xmcda/categories_values.py
xmcda/container.py
xmcda/criteria.py
xmcda/criteria_functions.py
xmcda/criteria_hierarchy.py
xmcda/criteria_matrix.py
xmcda/criteria_scales.py
xmcda/criteria_sets.py
xmcda/criteria_sets_hierarchy.py
xmcda/criteria_sets_values.py
xmcda/criteria_thresholds.py
xmcda/criteria_values.py
xmcda/description.py
xmcda/functions.py
xmcda/performance_table.py
xmcda/program_execution_result.py
xmcda/program_parameters.py
xmcda/scales.py
xmcda/schemas.py
xmcda/thresholds.py
xmcda/utils.py
xmcda/value.py
xmcda/mixins/__init__.py
xmcda/mixins/common_attributes.py
xmcda/mixins/description.py
xmcda/mixins/matrix.py
xmcda/mixins/set.py
xmcda/xsd/XMCDA-3.0.0.xsd
xmcda/xsd/XMCDA-3.0.1.xsd
xmcda/xsd/XMCDA-3.0.2.xsd
xmcda/xsd/XMCDA-3.1.0.xsd
xmcda/xsd/XMCDA-3.1.1.xsd
xmcda/xsd/XMCDA-4.0.0.xsd
xmcda-0.3.dist-info/LICENSE
xmcda-0.3.dist-info/METADATA
xmcda-0.3.dist-info/WHEEL
xmcda-0.3.dist-info/top_level.txt
xmcda-0.3.dist-info/RECORD
